{"nodes": [{"id": "app_api_admin_users_id_role_route_ts", "label": "route.ts", "file_type": "code", "source_file": "app/api/admin/users/[id]/role/route.ts", "source_location": "L1"}, {"id": "route_patch", "label": "PATCH()", "file_type": "code", "source_file": "app/api/admin/users/[id]/role/route.ts", "source_location": "L8"}], "edges": [{"source": "app_api_admin_users_id_role_route_ts", "target": "server", "relation": "imports_from", "confidence": "EXTRACTED", "source_file": "app/api/admin/users/[id]/role/route.ts", "source_location": "L1", "weight": 1.0}, {"source": "app_api_admin_users_id_role_route_ts", "target": "admin", "relation": "imports_from", "confidence": "EXTRACTED", "source_file": "app/api/admin/users/[id]/role/route.ts", "source_location": "L2", "weight": 1.0}, {"source": "app_api_admin_users_id_role_route_ts", "target": "server", "relation": "imports_from", "confidence": "EXTRACTED", "source_file": "app/api/admin/users/[id]/role/route.ts", "source_location": "L3", "weight": 1.0}, {"source": "app_api_admin_users_id_role_route_ts", "target": "route_patch", "relation": "contains", "confidence": "EXTRACTED", "source_file": "app/api/admin/users/[id]/role/route.ts", "source_location": "L8", "weight": 1.0}], "raw_calls": [{"caller_nid": "route_patch", "callee": "json", "source_file": "app/api/admin/users/[id]/role/route.ts", "source_location": "L15"}, {"caller_nid": "route_patch", "callee": "json", "source_file": "app/api/admin/users/[id]/role/route.ts", "source_location": "L18"}, {"caller_nid": "route_patch", "callee": "createServerClient", "source_file": "app/api/admin/users/[id]/role/route.ts", "source_location": "L21"}, {"caller_nid": "route_patch", "callee": "getUser", "source_file": "app/api/admin/users/[id]/role/route.ts", "source_location": "L22"}, {"caller_nid": "route_patch", "callee": "json", "source_file": "app/api/admin/users/[id]/role/route.ts", "source_location": "L25"}, {"caller_nid": "route_patch", "callee": "single", "source_file": "app/api/admin/users/[id]/role/route.ts", "source_location": "L29"}, {"caller_nid": "route_patch", "callee": "eq", "source_file": "app/api/admin/users/[id]/role/route.ts", "source_location": "L29"}, {"caller_nid": "route_patch", "callee": "select", "source_file": "app/api/admin/users/[id]/role/route.ts", "source_location": "L29"}, {"caller_nid": "route_patch", "callee": "from", "source_file": "app/api/admin/users/[id]/role/route.ts", "source_location": "L29"}, {"caller_nid": "route_patch", "callee": "includes", "source_file": "app/api/admin/users/[id]/role/route.ts", "source_location": "L37"}, {"caller_nid": "route_patch", "callee": "json", "source_file": "app/api/admin/users/[id]/role/route.ts", "source_location": "L38"}, {"caller_nid": "route_patch", "callee": "single", "source_file": "app/api/admin/users/[id]/role/route.ts", "source_location": "L42"}, {"caller_nid": "route_patch", "callee": "eq", "source_file": "app/api/admin/users/[id]/role/route.ts", "source_location": "L42"}, {"caller_nid": "route_patch", "callee": "select", "source_file": "app/api/admin/users/[id]/role/route.ts", "source_location": "L42"}, {"caller_nid": "route_patch", "callee": "from", "source_file": "app/api/admin/users/[id]/role/route.ts", "source_location": "L42"}, {"caller_nid": "route_patch", "callee": "json", "source_file": "app/api/admin/users/[id]/role/route.ts", "source_location": "L49"}, {"caller_nid": "route_patch", "callee": "includes", "source_file": "app/api/admin/users/[id]/role/route.ts", "source_location": "L55"}, {"caller_nid": "route_patch", "callee": "json", "source_file": "app/api/admin/users/[id]/role/route.ts", "source_location": "L56"}, {"caller_nid": "route_patch", "callee": "createAdminClient", "source_file": "app/api/admin/users/[id]/role/route.ts", "source_location": "L59"}, {"caller_nid": "route_patch", "callee": "eq", "source_file": "app/api/admin/users/[id]/role/route.ts", "source_location": "L62"}, {"caller_nid": "route_patch", "callee": "update", "source_file": "app/api/admin/users/[id]/role/route.ts", "source_location": "L62"}, {"caller_nid": "route_patch", "callee": "from", "source_file": "app/api/admin/users/[id]/role/route.ts", "source_location": "L62"}, {"caller_nid": "route_patch", "callee": "updateUserById", "source_file": "app/api/admin/users/[id]/role/route.ts", "source_location": "L70"}, {"caller_nid": "route_patch", "callee": "warn", "source_file": "app/api/admin/users/[id]/role/route.ts", "source_location": "L76"}, {"caller_nid": "route_patch", "callee": "json", "source_file": "app/api/admin/users/[id]/role/route.ts", "source_location": "L79"}, {"caller_nid": "route_patch", "callee": "error", "source_file": "app/api/admin/users/[id]/role/route.ts", "source_location": "L81"}, {"caller_nid": "route_patch", "callee": "json", "source_file": "app/api/admin/users/[id]/role/route.ts", "source_location": "L82"}]}